lk_logger/__init__.py
lk_logger/__main__.py
lk_logger/_screenshots/.gitkeep
lk_logger/cache/__init__.py
lk_logger/cache/cache.py
lk_logger/cache/frame.py
lk_logger/cache/legacy.py
lk_logger/cache/util.py
lk_logger/config.py
lk_logger/console.py
lk_logger/control.py
lk_logger/deflector.py
lk_logger/frame_info.py
lk_logger/logger.py
lk_logger/markup.py
lk_logger/message_builder.py
lk_logger/message_formatter.py
lk_logger/path_helper.py
lk_logger/printer.py
lk_logger/progress.py
lk_logger/scanner/__init__.py
lk_logger/scanner/analyser.py
lk_logger/scanner/const.py
lk_logger/scanner/exceptions.py
lk_logger/scanner/scanner.py
lk_logger/scanner/symbols.py
lk_logger/scanner/text_scanner.py
lk_logger/scanner/typehint.py
lk_logger/screenshot.py
lk_logger/sourcemap.py
lk_logger-6.0.6.dist-info/METADATA
lk_logger-6.0.6.dist-info/WHEEL
lk_logger-6.0.6.dist-info/RECORD
