Metadata-Version: 2.3
Name: lk-logger
Version: 6.0.6
Summary: Python print with source map and varnames.
License: MIT
Author: Likianta
Author-email: likianta@foxmail.com
Requires-Python: >=3.8,<4.0
Classifier: License :: OSI Approved :: MIT License
Classifier: Programming Language :: Python :: 3
Classifier: Programming Language :: Python :: 3.8
Classifier: Programming Language :: Python :: 3.9
Classifier: Programming Language :: Python :: 3.10
Classifier: Programming Language :: Python :: 3.11
Classifier: Programming Language :: Python :: 3.12
Classifier: Programming Language :: Python :: 3.13
Provides-Extra: ext
Requires-Dist: rich (>=13.8,<14.0)
Requires-Dist: svg-ultralight (>=0.34.0,<0.35.0) ; (python_version >= "3.9" and python_version < "4.0") and (extra == "ext")
Project-URL: Homepage, https://github.com/likianta/lk-logger
